markos/__init__.py
markos-0.0.4.dist-info/DESCRIPTION.rst
markos-0.0.4.dist-info/METADATA
markos-0.0.4.dist-info/RECORD
markos-0.0.4.dist-info/WHEEL
markos-0.0.4.dist-info/metadata.json
markos-0.0.4.dist-info/top_level.txt
